<?xml version="1.0" encoding="UTF-8"?>
<simpleviewerGallery maxImageWidth="480" maxImageHeight="480" textColor="0xffffff" frameColor="0xffffff" frameWidth="20" stagePadding="40" navPadding="40" thumbnailColumns="4" thumbnailRows="3" navPosition="left" vAlign="center" hAlign="center" title="Kenston" enableRightClickOpen="false" backgroundImagePath="" imagePath="" thumbPath="">
<image>
	<filename>IMG_1232.jpg</filename>
	<caption>IMG_1232.jpg</caption>
</image>
<image>
	<filename>IMG_1233.jpg</filename>
	<caption>IMG_1233.jpg</caption>
</image>
<image>
	<filename>IMG_1234.jpg</filename>
	<caption>IMG_1234.jpg</caption>
</image>
<image>
	<filename>IMG_1236.jpg</filename>
	<caption>IMG_1236.jpg</caption>
</image>
<image>
	<filename>IMG_1237.jpg</filename>
	<caption>IMG_1237.jpg</caption>
</image>
<image>
	<filename>IMG_1238.jpg</filename>
	<caption>IMG_1238.jpg</caption>
</image>
<image>
	<filename>IMG_1240.jpg</filename>
	<caption>IMG_1240.jpg</caption>
</image>
<image>
	<filename>IMG_1241.jpg</filename>
	<caption>IMG_1241.jpg</caption>
</image>
<image>
	<filename>IMG_1242.jpg</filename>
	<caption>IMG_1242.jpg</caption>
</image>
<image>
	<filename>IMG_1243.jpg</filename>
	<caption>IMG_1243.jpg</caption>
</image>
<image>
	<filename>IMG_1244.jpg</filename>
	<caption>IMG_1244.jpg</caption>
</image>
<image>
	<filename>IMG_1245.jpg</filename>
	<caption>IMG_1245.jpg</caption>
</image>
<image>
	<filename>IMG_1246.jpg</filename>
	<caption>IMG_1246.jpg</caption>
</image>
<image>
	<filename>IMG_1247.jpg</filename>
	<caption>IMG_1247.jpg</caption>
</image>
<image>
	<filename>IMG_1248.jpg</filename>
	<caption>IMG_1248.jpg</caption>
</image>
<image>
	<filename>IMG_1249.jpg</filename>
	<caption>IMG_1249.jpg</caption>
</image>
<image>
	<filename>IMG_1250.jpg</filename>
	<caption>IMG_1250.jpg</caption>
</image>
<image>
	<filename>IMG_1252.jpg</filename>
	<caption>IMG_1252.jpg</caption>
</image>
<image>
	<filename>IMG_1253.jpg</filename>
	<caption>IMG_1253.jpg</caption>
</image>
<image>
	<filename>IMG_1255.jpg</filename>
	<caption>IMG_1255.jpg</caption>
</image>
<image>
	<filename>IMG_1257.jpg</filename>
	<caption>IMG_1257.jpg</caption>
</image>
<image>
	<filename>IMG_1259.jpg</filename>
	<caption>IMG_1259.jpg</caption>
</image>
<image>
	<filename>IMG_1260.jpg</filename>
	<caption>IMG_1260.jpg</caption>
</image>
<image>
	<filename>IMG_1261.jpg</filename>
	<caption>IMG_1261.jpg</caption>
</image>
<image>
	<filename>IMG_1262.jpg</filename>
	<caption>IMG_1262.jpg</caption>
</image>
<image>
	<filename>IMG_1264.jpg</filename>
	<caption>IMG_1264.jpg</caption>
</image>
<image>
	<filename>IMG_1265.jpg</filename>
	<caption>IMG_1265.jpg</caption>
</image>
<image>
	<filename>IMG_1266.jpg</filename>
	<caption>IMG_1266.jpg</caption>
</image>
<image>
	<filename>IMG_1267.jpg</filename>
	<caption>IMG_1267.jpg</caption>
</image>
<image>
	<filename>IMG_1268.jpg</filename>
	<caption>IMG_1268.jpg</caption>
</image>
<image>
	<filename>IMG_1269.jpg</filename>
	<caption>IMG_1269.jpg</caption>
</image>
<image>
	<filename>IMG_1271.jpg</filename>
	<caption>IMG_1271.jpg</caption>
</image>
<image>
	<filename>IMG_1272.jpg</filename>
	<caption>IMG_1272.jpg</caption>
</image>
<image>
	<filename>IMG_1273.jpg</filename>
	<caption>IMG_1273.jpg</caption>
</image>
</simpleviewerGallery>